pysdtw/__init__.py
pysdtw/distance.py
pysdtw/sdtw_cpu.py
pysdtw/sdtw_cuda.py
pysdtw-0.0.5.dist-info/LICENSE
pysdtw-0.0.5.dist-info/METADATA
pysdtw-0.0.5.dist-info/WHEEL
pysdtw-0.0.5.dist-info/top_level.txt
pysdtw-0.0.5.dist-info/RECORD
