Metadata-Version: 2.1
Name: pysdtw
Version: 0.0.5
Summary: Torch implementation of Soft-DTW, supports CUDA devices.
Home-page: https://github.com/toinsson/pysdtw
Author: Antoine Loriette
Author-email: antoine.loriette@gmail.com
Requires-Python: >=3.7
License-File: LICENSE
Requires-Dist: torch
Requires-Dist: numba
